primeway_zipstream/__init__.py
primeway_zipstream/aiozipstream.py
primeway_zipstream/consts.py
primeway_zipstream/zipstream.py
primeway_zipstream-0.4.dist-info/METADATA
primeway_zipstream-0.4.dist-info/WHEEL
primeway_zipstream-0.4.dist-info/top_level.txt
primeway_zipstream-0.4.dist-info/RECORD
